zabbix2jira/__init__.py
zabbix2jira/cli.py
zabbix2jira/commands/__init__.py
zabbix2jira/commands/base.py
zabbix2jira/commands/clean.py
zabbix2jira/commands/problem.py
zabbix2jira-0.2.1.dist-info/DESCRIPTION.rst
zabbix2jira-0.2.1.dist-info/METADATA
zabbix2jira-0.2.1.dist-info/RECORD
zabbix2jira-0.2.1.dist-info/WHEEL
zabbix2jira-0.2.1.dist-info/entry_points.txt
zabbix2jira-0.2.1.dist-info/metadata.json
zabbix2jira-0.2.1.dist-info/top_level.txt
