Metadata-Version: 2.0
Name: zabbix2jira
Version: 0.2.1
Summary: Creates or updates a ticket on JIRA from Zabbix alarms
Home-page: https://github.com/Movile/zabbix2jira
Author: Hugo Cisneiros
Author-email: hugo.cisneiros@movile.com
License: GPL version 3
Keywords: zabbix,jira,tickets
Platform: UNKNOWN
Classifier: Intended Audience :: System Administrators
Classifier: Topic :: Utilities
Classifier: License :: OSI Approved :: GNU General Public License v3 (GPLv3)
Classifier: Natural Language :: English
Classifier: Operating System :: OS Independent
Classifier: Programming Language :: Python :: 2
Classifier: Programming Language :: Python :: 2.6
Classifier: Programming Language :: Python :: 2.7
Requires-Dist: docopt
Requires-Dist: jira
Requires-Dist: py-zabbix
Provides-Extra: test
Requires-Dist: nose; extra == 'test'
